{
    "State.Splash":"config/ui/layouts/State.Splash.json",
    "State.MainMenu":"config/ui/layouts/State.MainMenu.json",
    "State.About":"config/ui/layouts/State.About.json",
    "State.ConfirmQuit":"config/ui/layouts/State.ConfirmQuit.json",
    "State.Options":"config/ui/layouts/State.Options.json",
    "State.Start":"config/ui/layouts/State.Start.json",
    "State.Editor.Start":"config/ui/layouts/State.Editor.Start.json",
    "State.Editor.Scenarios":"config/ui/layouts/State.Editor.Scenarios.json",
    "State.Editor.Scenario":"config/ui/layouts/State.Editor.Scenario.json",
    "State.Editor.PickRoom":"config/ui/layouts/State.Editor.PickRoom.json",
    "State.Editor.NewRoom":"config/ui/layouts/State.Editor.NewRoom.json",
    "State.Editor.ScenarioDescriptor":"config/ui/layouts/State.Editor.ScenarioDescriptor.json",
    "State.Editor.RoomCells":"config/ui/layouts/State.Editor.RoomCells.json",
    "State.Editor.PickDescriptor":"config/ui/layouts/State.Editor.PickDescriptor.json",
    "State.Player.Start":"config/ui/layouts/State.Player.Start.json",
    "State.Player.NewGame":"config/ui/layouts/State.Player.NewGame.json",
    "State.Player.LoadGame":"config/ui/layouts/State.Player.LoadGame.json",
    "State.Editor.Avatar": "config/ui/layouts/State.Editor.Avatar.json"
}